dlt_runtime/__init__.py
dlt_runtime/__plugin__.py
dlt_runtime/_runtime_command.py
dlt_runtime/commands.py
dlt_runtime/exceptions.py
dlt_runtime/py.typed
dlt_runtime/runtime.py
dlt_runtime/version.py
dlt_runtime/runtime_clients/api/__init__.py
dlt_runtime/runtime_clients/api/client.py
dlt_runtime/runtime_clients/api/errors.py
dlt_runtime/runtime_clients/api/types.py
dlt_runtime/runtime_clients/api/api/__init__.py
dlt_runtime/runtime_clients/api/api/configurations/__init__.py
dlt_runtime/runtime_clients/api/api/configurations/create_configuration.py
dlt_runtime/runtime_clients/api/api/configurations/get_configuration.py
dlt_runtime/runtime_clients/api/api/configurations/get_latest_configuration.py
dlt_runtime/runtime_clients/api/api/configurations/list_configurations.py
dlt_runtime/runtime_clients/api/api/default/__init__.py
dlt_runtime/runtime_clients/api/api/default/ping.py
dlt_runtime/runtime_clients/api/api/deployments/__init__.py
dlt_runtime/runtime_clients/api/api/deployments/create_deployment.py
dlt_runtime/runtime_clients/api/api/deployments/get_deployment.py
dlt_runtime/runtime_clients/api/api/deployments/get_latest_deployment.py
dlt_runtime/runtime_clients/api/api/deployments/list_deployments.py
dlt_runtime/runtime_clients/api/api/me/__init__.py
dlt_runtime/runtime_clients/api/api/me/me.py
dlt_runtime/runtime_clients/api/api/organizations/__init__.py
dlt_runtime/runtime_clients/api/api/organizations/get_organization.py
dlt_runtime/runtime_clients/api/api/runs/__init__.py
dlt_runtime/runtime_clients/api/api/runs/cancel_run.py
dlt_runtime/runtime_clients/api/api/runs/create_run.py
dlt_runtime/runtime_clients/api/api/runs/get_latest_run.py
dlt_runtime/runtime_clients/api/api/runs/get_run.py
dlt_runtime/runtime_clients/api/api/runs/get_run_logs.py
dlt_runtime/runtime_clients/api/api/runs/list_runs.py
dlt_runtime/runtime_clients/api/api/scripts/__init__.py
dlt_runtime/runtime_clients/api/api/scripts/create_or_update_script.py
dlt_runtime-0.20.1.dist-info/METADATA
dlt_runtime-0.20.1.dist-info/WHEEL
dlt_runtime-0.20.1.dist-info/entry_points.txt
dlt_runtime-0.20.1.dist-info/licenses/LICENSE.txt
dlt_runtime-0.20.1.dist-info/RECORD
