Metadata-Version: 2.4
Name: dlt-runtime
Version: 0.20.1
Summary: CLI tool for accessing dltHub runtime
Author-email: "dltHub Inc." <services@dlthub.com>
Maintainer-email: Ivan Chebotar <ivan@dlthub.com>
License-Expression: Apache-2.0
License-File: LICENSE.txt
Keywords: etl
Classifier: Development Status :: 5 - Production/Stable
Classifier: Intended Audience :: Developers
Classifier: License :: OSI Approved :: Apache Software License
Classifier: Operating System :: MacOS :: MacOS X
Classifier: Operating System :: Microsoft :: Windows
Classifier: Operating System :: POSIX :: Linux
Classifier: Programming Language :: Python :: 3.9
Classifier: Programming Language :: Python :: 3.10
Classifier: Programming Language :: Python :: 3.11
Classifier: Programming Language :: Python :: 3.12
Classifier: Programming Language :: Python :: 3.13
Classifier: Topic :: Software Development :: Libraries
Classifier: Typing :: Typed
Requires-Python: <3.15,>=3.9.2
Requires-Dist: attrs>=23.2.0
Requires-Dist: cron-descriptor>=1.2.32
Requires-Dist: httpx>=0.26.0
Requires-Dist: pathspec>=0.11.2
Requires-Dist: python-jose>=3.5.0
Requires-Dist: tabulate>=0.9.0
